fastdatasets/__init__.py
fastdatasets/arrow/__init__.py
fastdatasets/arrow/dataset.py
fastdatasets/arrow/default.py
fastdatasets/arrow/writer.py
fastdatasets/arrow/iterable_dataset/__init__.py
fastdatasets/arrow/iterable_dataset/ds.py
fastdatasets/arrow/random_dataset/__init__.py
fastdatasets/arrow/random_dataset/ds.py
fastdatasets/common/__init__.py
fastdatasets/common/iterable_dataset.py
fastdatasets/common/random_dataset.py
fastdatasets/common/writer.py
fastdatasets/common/writer_object.py
fastdatasets/leveldb/__init__.py
fastdatasets/leveldb/dataset.py
fastdatasets/leveldb/default.py
fastdatasets/leveldb/writer.py
fastdatasets/leveldb/iterable_dataset/__init__.py
fastdatasets/leveldb/iterable_dataset/ds.py
fastdatasets/leveldb/random_dataset/__init__.py
fastdatasets/leveldb/random_dataset/ds.py
fastdatasets/lmdb/__init__.py
fastdatasets/lmdb/dataset.py
fastdatasets/lmdb/default.py
fastdatasets/lmdb/writer.py
fastdatasets/lmdb/iterable_dataset/__init__.py
fastdatasets/lmdb/iterable_dataset/ds.py
fastdatasets/lmdb/random_dataset/__init__.py
fastdatasets/lmdb/random_dataset/ds.py
fastdatasets/memory/__init__.py
fastdatasets/memory/dataset.py
fastdatasets/memory/writer.py
fastdatasets/memory/iterable_dataset/__init__.py
fastdatasets/memory/iterable_dataset/ds.py
fastdatasets/memory/random_dataset/__init__.py
fastdatasets/memory/random_dataset/ds.py
fastdatasets/parquet/__init__.py
fastdatasets/parquet/dataset.py
fastdatasets/parquet/default.py
fastdatasets/parquet/writer.py
fastdatasets/parquet/iterable_dataset/__init__.py
fastdatasets/parquet/iterable_dataset/ds.py
fastdatasets/parquet/random_dataset/__init__.py
fastdatasets/parquet/random_dataset/ds.py
fastdatasets/record/__init__.py
fastdatasets/record/dataset.py
fastdatasets/record/default.py
fastdatasets/record/writer.py
fastdatasets/record/iterable_dataset/__init__.py
fastdatasets/record/iterable_dataset/ds.py
fastdatasets/record/random_dataset/__init__.py
fastdatasets/record/random_dataset/ds.py
fastdatasets-0.10.0.dist-info/METADATA
fastdatasets-0.10.0.dist-info/WHEEL
fastdatasets-0.10.0.dist-info/top_level.txt
fastdatasets-0.10.0.dist-info/RECORD
