Metadata-Version: 2.1
Name: fastdatasets
Version: 0.10.0
Summary: fastdatasets: datasets for tfrecords
Home-page: https://github.com/ssbuild/fastdatasets
Author: ssbuild
Author-email: 9727464@qq.com
License: Apache 2.0
Keywords: fastdatasets,tfrecords,dataset,datasets
Platform: UNKNOWN
Classifier: Development Status :: 5 - Production/Stable
Classifier: Intended Audience :: Developers
Classifier: Intended Audience :: Education
Classifier: Intended Audience :: Science/Research
Classifier: License :: OSI Approved :: Apache Software License
Classifier: Programming Language :: C++
Classifier: Programming Language :: Python :: 3
Classifier: Programming Language :: Python :: 3.10
Classifier: Programming Language :: Python :: 3.11
Classifier: Programming Language :: Python :: 3.12
Classifier: Programming Language :: Python :: 3.13
Classifier: Topic :: Scientific/Engineering
Classifier: Topic :: Scientific/Engineering :: Mathematics
Classifier: Topic :: Scientific/Engineering :: Artificial Intelligence
Classifier: Topic :: Software Development
Classifier: Topic :: Software Development :: Libraries
Classifier: Topic :: Software Development :: Libraries :: Python Modules
Requires-Python: >=3, <4
Requires-Dist: tfrecords <0.4,>=0.3.0
Requires-Dist: data-serialize >=0.2.1
Requires-Dist: numpy
